README.rst
pyproject.toml
setup.py
kraken/__init__.py
kraken/common/__init__.py
kraken/common/config/__init__.py
kraken/common/config/config.py
kraken/common/core/__init__.py
kraken/common/core/exception.py
kraken/common/model/__init__.py
kraken/common/model/execution_type.py
kraken/common/model/job.py
kraken/common/model/task.py
kraken/common/model/worker.py
kraken/common/utils/__init__.py
kraken/common/utils/glob.py
kraken/common/utils/utils.py
kraken/filesystem/__init__.py
kraken/filesystem/config.py
kraken/filesystem/filesystem.py
kraken/filesystem/filesystem_factory.py
kraken/filesystem/ioutils.py
kraken/filesystem/gcp/__init__.py
kraken/filesystem/gcp/filesystem.py
kraken/filesystem/hdfs/__init__.py
kraken/filesystem/hdfs/filesystem.py
kraken/filesystem/local/__init__.py
kraken/filesystem/local/local_filesystem.py
kraken/filesystem/local/remote_filesystem.py
kraken/filesystem/s3/__init__.py
kraken/filesystem/s3/filesystem.py
kraken/master/__init__.py
kraken/master/client/__init__.py
kraken/master/client/__main__.py
kraken/master/client/client.py
kraken/master/config/__init__.py
kraken/master/config/config.py
kraken/master/core/__init__.py
kraken/master/core/dispatcher.py
kraken/master/core/master.py
kraken/master/core/scheduler.py
kraken/master/core/execution/__init__.py
kraken/master/core/execution/execution_job.py
kraken/master/core/execution/execution_manager.py
kraken/master/core/execution/execution_state.py
kraken/master/core/execution/job_factory.py
kraken/master/core/worker/__init__.py
kraken/master/core/worker/worker.py
kraken/master/core/worker/worker_decommissioner.py
kraken/master/core/worker/worker_factory.py
kraken/master/core/worker/worker_manager.py
kraken/master/core/worker/worker_monitor.py
kraken/master/server/__init__.py
kraken/master/server/__main__.py
kraken/master/server/handler.py
kraken/master/server/server.py
kraken/master/standalone/__init__.py
kraken/master/standalone/master.py
kraken/master/standalone/worker.py
kraken_pyds.egg-info/PKG-INFO
kraken_pyds.egg-info/SOURCES.txt
kraken_pyds.egg-info/dependency_links.txt
kraken_pyds.egg-info/entry_points.txt
kraken_pyds.egg-info/requires.txt
kraken_pyds.egg-info/top_level.txt
