Metadata-Version: 2.1
Name: kraken-pyds
Version: 2.0.1
Summary: kraken: python distributed data transfer tool.
Home-page: https://github.com/yassineazzouz/kraken
Author: Yassine Azzouz
Author-email: yassine.azzouz@agmail.com
License: MIT
Keywords: thrift python kraken hdfs
Platform: UNKNOWN
Classifier: Topic :: Software Development
Classifier: Development Status :: 5 - Production/Stable
Classifier: Intended Audience :: Developers
Classifier: Intended Audience :: System Administrators
Classifier: License :: OSI Approved :: MIT License
Classifier: Programming Language :: Python :: 2
Classifier: Programming Language :: Python :: 2.7
Classifier: Programming Language :: Python :: 3
Classifier: Programming Language :: Python :: 3.5
Classifier: Programming Language :: Python :: 3.6
Classifier: Programming Language :: Python :: 3.7
Classifier: Programming Language :: Python :: 3.8
Requires-Python: >=2.7, !=3.0.*, !=3.1.*, !=3.2.*, !=3.3.*, !=3.4.*
